gemparser/__init__.py
gemparser-0.1.dist-info/DESCRIPTION.rst
gemparser-0.1.dist-info/METADATA
gemparser-0.1.dist-info/metadata.json
gemparser-0.1.dist-info/RECORD
gemparser-0.1.dist-info/top_level.txt
gemparser-0.1.dist-info/WHEEL
