Metadata-Version: 2.0
Name: gemparser
Version: 0.1
Summary: Parse Ruby Gemfiles
Home-page: https://github.com/mfwarren/gemparser
Author: Matt Warren
Author-email: matt.warren@gmail.com
License: MIT
Keywords: ruby gems gemfile gemspec
Platform: UNKNOWN
Classifier: Development Status :: 3 - AlphaProgramming Language :: Python :: 2.6
Classifier: Programming Language :: Python :: 2.7
Classifier: Programming Language :: Python :: 3.2
Classifier: Programming Language :: Python :: 3.3
Classifier: Programming Language :: Python :: 3.4
Classifier: Programming Language :: RubyIntended Audience :: Developers
Classifier: License :: OSI Approved :: MIT License
Classifier: Operating System :: OS Independent
Classifier: Topic :: Software Development :: Libraries :: Ruby Modules
